keydope/__init__.py
keydope/devices.py
keydope/eventloop.py
keydope/key_dist.py
keydope/key_parsing.py
keydope/keycodes.py
keydope/keymap.py
keydope/keymap_config.py
keydope/mods.py
keydope/session.py
keydope/stats.py
keydope/transform.py
keydope/util.py
keydope-0.2.0a2.dist-info/LICENSE
keydope-0.2.0a2.dist-info/WHEEL
keydope-0.2.0a2.dist-info/METADATA
keydope-0.2.0a2.dist-info/RECORD
